requirements.txt
medvedi/__init__.py
medvedi/accelerators.cpython-310-x86_64-linux-gnu.so
medvedi/accelerators.pyx
medvedi/dataframe.py
medvedi/io.cpython-310-x86_64-linux-gnu.so
medvedi/io.pyx
medvedi/libmimalloc.so
medvedi/libmimalloc.so.2
medvedi/libmimalloc.so.2.1
medvedi/merge_to_str.py
medvedi/metadata.py
medvedi/mimalloc.h
medvedi/pure_static.py
medvedi/testing.py
medvedi/native/__init__.py
medvedi/native/chunked_stream.h
medvedi/native/chunked_stream.pxd
medvedi/native/cpython.pxd
medvedi/native/memnrchr.h
medvedi/native/mi_heap_destroy_stl_allocator.cpython-310-x86_64-linux-gnu.so
medvedi/native/mi_heap_destroy_stl_allocator.h
medvedi/native/mi_heap_destroy_stl_allocator.pxd
medvedi/native/mi_heap_destroy_stl_allocator.pyx
medvedi/native/numpy.pxd
medvedi/native/optional.pxd
medvedi/native/sorted_intersection.h
medvedi/native/string_view.pxd
medvedi/native/utf8.pxd
medvedi-0.1.68.dist-info/LICENSE
medvedi-0.1.68.dist-info/METADATA
medvedi-0.1.68.dist-info/WHEEL
medvedi-0.1.68.dist-info/top_level.txt
medvedi-0.1.68.dist-info/RECORD
