Metadata-Version: 2.1
Name: medvedi
Version: 0.1.68
Summary: Memory Efficient Deconstructed Vectorized Dataframe Interface
Home-page: https://github.com/athenianco/medvedi
Download-URL: https://github.com/athenianco/medvedi
Author: Athenian
Author-email: vadim@athenian.co
License: Apache 2.0
Classifier: Development Status :: 3 - Alpha
Classifier: Programming Language :: Python :: 3.10
Classifier: Programming Language :: Python :: 3.11
Classifier: Programming Language :: Python :: 3.12
License-File: LICENSE
Requires-Dist: numpy<2.0,>=1.23
Requires-Dist: pyarrow>=14.0.0
Provides-Extra: arrow
Requires-Dist: pyarrow; extra == "arrow"
